ev_ui/__init__.py
ev_ui/ev.py
ev_ui-0.0.7.dist-info/LICENSE
ev_ui-0.0.7.dist-info/METADATA
ev_ui-0.0.7.dist-info/WHEEL
ev_ui-0.0.7.dist-info/entry_points.txt
ev_ui-0.0.7.dist-info/top_level.txt
ev_ui-0.0.7.dist-info/RECORD
